apdaily/__init__.py
apdaily/main.py
apdaily_methods/__init__.py
apdaily_methods/apdaily_m1.py
apdaily_methods/mouse_util.py
apdaily_startup/__init__.py
apdaily_startup/apdaily_startup_main.py
apdaily-1.0.6.dist-info/METADATA
apdaily-1.0.6.dist-info/WHEEL
apdaily-1.0.6.dist-info/top_level.txt
apdaily-1.0.6.dist-info/RECORD
