Metadata-Version: 2.1
Name: apdaily
Version: 1.0.6
Summary: A package that allows you to watch AP Classroom Daily videos automatically.
Home-page: https://github.com/SarangaR/APDaily-Dev
Author: Fdhsy
License: : OSI Approved :: MIT License
Requires-Python: >=3.6
Requires-Dist: pynput
Requires-Dist: toml
